{
  "contract_name": "treatment_control",
  "version": "1.0",
  "options": {
    "mask_zone_codes": [
      "Forehead Zone",
      "Periorbital Zone",
      "Nasal Zone",
      "Left Malar Zone",
      "Right Malar Zone",
      "Perioral Zone",
      "Mandibular/Chin Zone",
      "Jawline Zone"
    ],
    "light_color_codes": [
      "red",
      "orange",
      "yellow",
      "green",
      "cyan",
      "blue",
      "purple"
    ],
    "brightness_percent": {
      "min": 0,
      "max": 100,
      "step": 1,
      "unit": "percent"
    },
    "temperature_celsius": {
      "min": 20,
      "max": 40,
      "step": 1,
      "unit": "celsius"
    },
    "humidification_frequency_level": {
      "min": 0,
      "max": 100,
      "step": 1,
      "unit": "level"
    },
    "timer_minutes": {
      "min": 1,
      "max": 60,
      "step": 1,
      "unit": "minutes"
    }
  },
  "control_session": {
    "schema_version": "mask_control.v1",
    "execution_channel": "reserved",
    "treatment_plan_id": "string",
    "user_public_id": "string",
    "overall_severity": "low | medium | high",
    "summary_texts": {
      "en": "string",
      "zh": "string"
    },
    "global_settings": {
      "brightness_percent": 0,
      "temperature_celsius": 0,
      "humidification_frequency_level": 0,
      "timer_minutes": 0
    },
    "zone_led_settings": [
      {
        "zone_name": "Forehead Zone",
        "issue_category_code": "string",
        "severity": "low | medium | high",
        "led_color_code": "red | orange | yellow | green | cyan | blue | purple"
      }
    ]
  }
}
